MANIFEST.in
README.rst
setup.py
src/object_cacher.py
src/object_cacher.egg-info/PKG-INFO
src/object_cacher.egg-info/SOURCES.txt
src/object_cacher.egg-info/dependency_links.txt
src/object_cacher.egg-info/top_level.txt