Metadata-Version: 1.1
Name: object-cacher
Version: 0.3.1
Summary: Simple objects/methods results cacher with optional persistent cacheing. Supports Memory Files or Redis as storage
Home-page: http://github.com/mosquito/object_cacher
Author: Dmitry Orlov <me@mosquito.su>
Author-email: me@mosquito.su
License: MIT
Platform: all
Classifier: Environment :: Console
Classifier: Programming Language :: Python
